jobdone/__init__.py
jobdone/__main__.py
jobdone/feed.py
jobdone/viewer.py
python_jobdone-1.0.0.dist-info/LICENSE
python_jobdone-1.0.0.dist-info/METADATA
python_jobdone-1.0.0.dist-info/WHEEL
python_jobdone-1.0.0.dist-info/entry_points.txt
python_jobdone-1.0.0.dist-info/top_level.txt
python_jobdone-1.0.0.dist-info/RECORD
