Metadata-Version: 2.1
Name: python-jobdone
Version: 1.0.0
Summary: This is unofficial python library for jobdone.net
Home-page: https://github.com/krakiun/python-jobdone
Author: krakiun
Author-email: krakiun@gmail.com
License: MIT
Platform: UNKNOWN
Classifier: License :: OSI Approved :: MIT License
Classifier: Programming Language :: Python
Classifier: Programming Language :: Python :: 2
Classifier: Programming Language :: Python :: 3
License-File: LICENSE
Requires-Dist: requests
Requires-Dist: importlib-resources
Requires-Dist: typing
